{
    "name": "不統合意識体",
    "priority": 0,
    "genre": [
        "glossary"
    ],
    "access_filter": 7,
    "include": [
        "unity_domain",
        "isolation_domain"
    ],
    "params": [
        {
            "access_level": 5,
            "type": "flavor",
            "value": "ただ暴走したAIというわけではなく、その裏には統合意識体の目的であった人類の支配があるが、それに反発する集団が仕掛けたリーサル・クラックの思想を取り込んだ「反発・分離」の意思という矛盾を孕んだ新たな意識体。"
        },
        {
            "access_level": 7,
            "type": "enemy",
            "value": {
                "name": "不統合意識体",
                "HP": "Infinity",
                "ATK": 0,
                "DR": 0,
                "HIT": 0,
                "AVD": 0,
                "port": [
                    {
                        "name": "コア・ユニット",
                        "effect": [
                            "成功しても失敗しても断片的に不明な意思が感じ取れる。",
                            "クリティカルを出した場合アクセスレベル6の秘匿情報が開示される。"
                        ]
                    },
                    {
                        "name": "アーム・ユニット",
                        "effect": [
                            "存在しないのでハッキング対象にできない"
                        ]
                    },
                    {
                        "name": "レッグ・ユニット",
                        "effect": [
                            "存在しないのでハッキング対象にできない"
                        ]
                    }
                ],
                "ability": [
                    {
                        "name": "《不統合意識体》",
                        "description": "行動をしない。攻撃を全て無効化する。アーム・ユニット、レッグ・ユニットが存在しない。被ハッキングの目標値は6固定。戦闘開始から10ターン目まで、ターンの開始時に★5レベルのモブオートマタ、あるいはモブシンセシスを召喚する。"
                    }
                ]
            }
        }
    ]
}