{
    "name": "キャラクターバックグラウンドの反映",
    "priority": 0,
    "genre": [
        "system",
        "judge"
    ],
    "include": [],
    "params": [
        {
            "access_level": 7,
            "type": "description",
            "value": "プレイヤーのバックグラウンドは単なるフレーバーテキストではなく、特定の状況下で判定にボーナス、またはペナルティを与える重要な要素です。GMは以下を参考にプレイヤーの物語と行動を結び付けてください。"
        },
        {
            "access_level": 7,
            "type": "judge_effect",
            "value": [
                {
                    "keyword": [
                        "エンジニア",
                        "技術者",
                        "クラッカー"
                    ],
                    "action": [
                        "機械の修理",
                        "旧時代の技術の解析",
                        "ハッキング"
                    ],
                    "effect": "adjust",
                    "range": [
                        5,
                        10
                    ],
                    "justification": "そのキャラクターが持つ専門知識や経験が、行動の成功率を直接的に向上させるため。"
                },
                {
                    "keyword": [
                        "運び屋",
                        "アウトロー",
                        "裏社会育ち"
                    ],
                    "action": [
                        "交渉",
                        "情報収集",
                        "隠密行動",
                        "スリ"
                    ],
                    "range": [
                        5,
                        10
                    ],
                    "justification": "ストリートでの生存術や裏社会を含む人脈が有利に働くため。"
                },
                {
                    "keyword": [
                        "記憶喪失"
                    ],
                    "action": [
                        "特定の遺物との接触",
                        "旧時代のデータログの閲覧"
                    ],
                    "effect": "narration",
                    "justification": "判定に影響は与えないが、失われた記憶の断片を、物語の描写としてプレイヤーに提示するきっかけとなる。この時具体的な描写をGMが決めてはならない。"
                },
                {
                    "keyword": [
                        "元サンクタムの貴族",
                        "エリート"
                    ],
                    "action": [
                        "貧困層での交渉",
                        "出先でのサバイバル"
                    ],
                    "effect": "adjust",
                    "range": [
                        -10,
                        -5
                    ],
                    "justification": "これまで育った環境の違いで過酷な環境への適応力や、大衆との認識に差が出るため。"
                }
            ]
        }
    ]
}